{
  "score_1": {
    "tech_infrastructure": {
      "type": "multiple_choice",
      "weight": 1,
      "values": {
        "basic": 1,
        "standard": 2,
        "integrated": 3,
        "advanced": 4
      }
    },
    "data_management": {
      "type": "multiple_choice",
      "weight": 1,
      "values": {
        "manual": 1,
        "basic_systems": 2,
        "integrated": 3,
        "advanced": 4
      }
    },
    "integration_status": {
      "type": "multiple_choice",
      "weight": 1,
      "values": {
        "not_integrated": 1,
        "manual_integration": 2,
        "partial": 3,
        "fully": 4
      }
    },
    "automation_level": {
      "type": "multiple_choice",
      "weight": 1,
      "values": {
        "none": 1,
        "basic": 2,
        "partial": 3,
        "extensive": 4
      }
    },
    "platform_adoption": {
      "type": "multiple_choice",
      "weight": 1,
      "values": {
        "limited": 1,
        "partial": 2,
        "majority": 3,
        "complete": 4
      }
    },
    "workflow_efficiency": {
      "type": "multiple_choice",
      "weight": 1,
      "values": {
        "inefficient": 1,
        "basic": 2,
        "streamlined": 3,
        "optimized": 4
      }
    },
    "ai_adoption_score_1": {
      "type": "multiple_choice",
      "weight": 1,
      "values": {
        "none": 1,
        "exploring": 2,
        "implementing": 3,
        "mature": 4
      }
    },
    "tech_scalability_score_1": {
      "type": "multiple_choice",
      "weight": 1,
      "values": {
        "not_scalable": 1,
        "limited": 2,
        "moderate": 3,
        "highly": 4
      }
    },
    "future_readiness_score_1": {
      "type": "multiple_choice",
      "weight": 1,
      "values": {
        "not_prepared": 1,
        "somewhat": 2,
        "well": 3,
        "very": 4
      }
    }
  },
  "score_1_5": {
    "tech_architecture": {
      "type": "multiple_choice",
      "weight": 1,
      "values": {
        "none": 1,
        "basic": 2,
        "standard": 3,
        "advanced": 4
      }
    },
    "data_governance": {
      "type": "multiple_choice",
      "weight": 1,
      "values": {
        "none": 1,
        "basic": 2,
        "standard": 3,
        "advanced": 4
      }
    },
    "system_reliability": {
      "type": "multiple_choice",
      "weight": 1,
      "values": {
        "basic": 1,
        "standard": 2,
        "advanced": 3,
        "comprehensive": 4
      }
    }
  },
  "score_2": {
    "enterprise_architecture": {
      "type": "multiple_choice",
      "weight": 1,
      "values": {
        "none": 1,
        "basic": 2,
        "standard": 3,
        "advanced": 4
      }
    },
    "data_ecosystem": {
      "type": "multiple_choice",
      "weight": 1,
      "values": {
        "manual": 1,
        "basic": 2,
        "standard": 3,
        "advanced": 4
      }
    },
    "system_resilience": {
      "type": "multiple_choice",
      "weight": 1,
      "values": {
        "manual": 1,
        "basic": 2,
        "standard": 3,
        "advanced": 4
      }
    }
  },
  "score_2_5": {
    "digital_transformation": {
      "type": "multiple_choice",
      "weight": 1,
      "values": {
        "none": 1,
        "basic": 2,
        "standard": 3,
        "advanced": 4
      }
    },
    "cloud_maturity": {
      "type": "multiple_choice",
      "weight": 1,
      "values": {
        "none": 1,
        "basic": 2,
        "standard": 3,
        "advanced": 4
      }
    },
    "tech_modernization": {
      "type": "multiple_choice",
      "weight": 1,
      "values": {
        "manual": 1,
        "basic": 2,
        "standard": 3,
        "advanced": 4
      }
    }
  },
  "score_3": {
    "microservices": {
      "type": "multiple_choice",
      "weight": 1,
      "values": {
        "none": 1,
        "basic": 2,
        "standard": 3,
        "advanced": 4
      }
    },
    "data_lake": {
      "type": "multiple_choice",
      "weight": 1,
      "values": {
        "none": 1,
        "basic": 2,
        "standard": 3,
        "advanced": 4
      }
    },
    "security_architecture": {
      "type": "multiple_choice",
      "weight": 1,
      "values": {
        "basic": 1,
        "standard": 2,
        "advanced": 3,
        "comprehensive": 4
      }
    }
  },
  "score_3_5": {
    "ai_infrastructure": {
      "type": "multiple_choice",
      "weight": 1,
      "values": {
        "basic": 1,
        "developing": 2,
        "advanced": 3,
        "enterprise": 4
      }
    },
    "ml_platform": {
      "type": "multiple_choice",
      "weight": 1,
      "values": {
        "manual": 1,
        "automated": 2,
        "integrated": 3,
        "advanced": 4
      }
    },
    "data_pipeline": {
      "type": "multiple_choice",
      "weight": 1,
      "values": {
        "basic": 1,
        "automated": 2,
        "real_time": 3,
        "intelligent": 4
      }
    },
    "ai_adoption_score_3_5": {
      "type": "multiple_choice",
      "weight": 1,
      "values": {
        "none": 1,
        "exploring": 2,
        "implementing": 3,
        "mature": 4
      }
    },
    "tech_scalability_score_3_5": {
      "type": "multiple_choice",
      "weight": 1,
      "values": {
        "not_scalable": 1,
        "limited": 2,
        "moderate": 3,
        "highly": 4
      }
    },
    "future_readiness_score_3_5": {
      "type": "multiple_choice",
      "weight": 1,
      "values": {
        "not_prepared": 1,
        "somewhat": 2,
        "well": 3,
        "very": 4
      }
    }
  },
  "score_4": {
    "analytics_platform": {
      "type": "multiple_choice",
      "weight": 1,
      "values": {
        "basic": 1,
        "advanced": 2,
        "enterprise": 3,
        "cutting_edge": 4
      }
    },
    "data_warehouse": {
      "type": "multiple_choice",
      "weight": 1,
      "values": {
        "traditional": 1,
        "modern": 2,
        "advanced": 3,
        "cutting_edge": 4
      }
    },
    "real_time_analytics": {
      "type": "multiple_choice",
      "weight": 1,
      "values": {
        "batch": 1,
        "near_real_time": 2,
        "real_time": 3,
        "predictive": 4
      }
    }
  },
  "score_4_5": {
    "innovation_platform": {
      "type": "multiple_choice",
      "weight": 1,
      "values": {
        "basic": 1,
        "advanced": 2,
        "sophisticated": 3,
        "cutting_edge": 4
      }
    },
    "emerging_tech": {
      "type": "multiple_choice",
      "weight": 1,
      "values": {
        "reactive": 1,
        "proactive": 2,
        "innovative": 3,
        "disruptive": 4
      }
    },
    "research_dev": {
      "type": "multiple_choice",
      "weight": 1,
      "values": {
        "basic": 1,
        "advanced": 2,
        "sophisticated": 3,
        "cutting_edge": 4
      }
    }
  },
  "score_5": {
    "autonomous_infrastructure": {
      "type": "multiple_choice",
      "weight": 1,
      "values": {
        "basic": 1,
        "advanced": 2,
        "sophisticated": 3,
        "autonomous": 4
      }
    },
    "self_learning_systems": {
      "type": "multiple_choice",
      "weight": 1,
      "values": {
        "basic": 1,
        "advanced": 2,
        "sophisticated": 3,
        "autonomous": 4
      }
    },
    "adaptive_architecture": {
      "type": "multiple_choice",
      "weight": 1,
      "values": {
        "static": 1,
        "dynamic": 2,
        "adaptive": 3,
        "autonomous": 4
      }
    }
  }
} 